LICENSE
MANIFEST.in
README.rst
production.ini
setup.py
data/trololo.ogg
mattd/__init__.py
mattd.d/main.ini
mattd.d/mplayer.ini
mattd.plugins.mplayer.egg-info/PKG-INFO
mattd.plugins.mplayer.egg-info/SOURCES.txt
mattd.plugins.mplayer.egg-info/dependency_links.txt
mattd.plugins.mplayer.egg-info/entry_points.txt
mattd.plugins.mplayer.egg-info/namespace_packages.txt
mattd.plugins.mplayer.egg-info/not-zip-safe
mattd.plugins.mplayer.egg-info/requires.txt
mattd.plugins.mplayer.egg-info/top_level.txt
mattd/plugins/__init__.py
mattd/plugins/mplayer/__init__.py